Metadata-Version: 2.4
Name: fhdocx
Version: 0.1.7
Summary: *fh-docx* is a Python library for reading, creating, and updating Microsoft Word 2007+ (.docx) files.
Author: wsd
Author-email: wsd@fhit.cn
Requires-Python: >=3.9
Classifier: Programming Language :: Python :: 3
Classifier: Programming Language :: Python :: 3.9
Classifier: Programming Language :: Python :: 3.10
Classifier: Programming Language :: Python :: 3.11
Classifier: Programming Language :: Python :: 3.12
Classifier: Programming Language :: Python :: 3.13
Classifier: Programming Language :: Python :: 3.14
Requires-Dist: lxml (>=6.0.2,<7.0.0)
Requires-Dist: python-pptx (>=1.0.2,<2.0.0)
Requires-Dist: typing-extensions (>=4.15.0,<5.0.0)
